iterative_telemetry/__init__.py
iterative_telemetry-0.0.9.dist-info/LICENSE
iterative_telemetry-0.0.9.dist-info/METADATA
iterative_telemetry-0.0.9.dist-info/WHEEL
iterative_telemetry-0.0.9.dist-info/top_level.txt
iterative_telemetry-0.0.9.dist-info/RECORD
