Metadata-Version: 2.1
Name: iterative-telemetry
Version: 0.0.9
Summary: Common library for sending telemetry
Home-page: https://github.com/iterative/telemetry-python
Maintainer-email: support@dvc.org
License: Apache-2.0
Platform: any
Classifier: Programming Language :: Python :: 3
Classifier: Programming Language :: Python :: 3.8
Classifier: Programming Language :: Python :: 3.9
Classifier: Programming Language :: Python :: 3.10
Classifier: Programming Language :: Python :: 3.11
Classifier: Development Status :: 4 - Beta
Requires-Python: >=3.8
License-File: LICENSE
Requires-Dist: requests
Requires-Dist: appdirs
Requires-Dist: filelock
Requires-Dist: distro
Provides-Extra: tests
Requires-Dist: pytest==7.2.0; extra == "tests"
Requires-Dist: pytest-sugar==0.9.5; extra == "tests"
Requires-Dist: pytest-cov==3.0.0; extra == "tests"
Requires-Dist: pytest-mock==3.8.2; extra == "tests"
Requires-Dist: pylint==2.15.0; extra == "tests"
Requires-Dist: mypy==1.11.2; extra == "tests"
Requires-Dist: types-requests; extra == "tests"
Provides-Extra: dev
Requires-Dist: pytest==7.2.0; extra == "dev"
Requires-Dist: pytest-sugar==0.9.5; extra == "dev"
Requires-Dist: pytest-cov==3.0.0; extra == "dev"
Requires-Dist: pytest-mock==3.8.2; extra == "dev"
Requires-Dist: pylint==2.15.0; extra == "dev"
Requires-Dist: mypy==1.11.2; extra == "dev"
Requires-Dist: types-requests; extra == "dev"
